{"nodes": [{"id": "tools_configurations", "label": "configurations.ts", "file_type": "code", "source_file": "src/tools/configurations.ts", "source_location": null, "source_url": null, "captured_at": null, "author": null, "contributor": null}], "edges": [{"source": "tools_configurations", "target": "tools_devices", "relation": "shares_data_with", "confidence": "INFERRED", "confidence_score": 0.65, "source_file": "src/tools/configurations.ts", "source_location": null, "weight": 1.0}], "hyperedges": []}